<annotation>
	<folder>train</folder>
	<filename>images_27.jpg</filename>
	<path>D:\Tensorflow\models\research\object_detection\images\train\images_27.jpg</path>
	<source>
		<database>Unknown</database>
	</source>
	<size>
		<width>1478</width>
		<height>1108</height>
		<depth>3</depth>
	</size>
	<segmented>0</segmented>
	<object>
		<name>clubs</name>
		<pose>Unspecified</pose>
		<truncated>0</truncated>
		<difficult>0</difficult>
		<bndbox>
			<xmin>635</xmin>
			<ymin>511</ymin>
			<xmax>703</xmax>
			<ymax>575</ymax>
		</bndbox>
	</object>
	<object>
		<name>clubs</name>
		<pose>Unspecified</pose>
		<truncated>0</truncated>
		<difficult>0</difficult>
		<bndbox>
			<xmin>673</xmin>
			<ymin>608</ymin>
			<xmax>705</xmax>
			<ymax>640</ymax>
		</bndbox>
	</object>
	<object>
		<name>clubs</name>
		<pose>Unspecified</pose>
		<truncated>0</truncated>
		<difficult>0</difficult>
		<bndbox>
			<xmin>853</xmin>
			<ymin>490</ymin>
			<xmax>913</xmax>
			<ymax>561</ymax>
		</bndbox>
	</object>
	<object>
		<name>clubs</name>
		<pose>Unspecified</pose>
		<truncated>0</truncated>
		<difficult>0</difficult>
		<bndbox>
			<xmin>850</xmin>
			<ymin>429</ymin>
			<xmax>882</xmax>
			<ymax>466</ymax>
		</bndbox>
	</object>
</annotation>
