<annotation>
	<folder>train</folder>
	<filename>images_17.jpg</filename>
	<path>D:\Tensorflow\models\research\object_detection\images\train\images_17.jpg</path>
	<source>
		<database>Unknown</database>
	</source>
	<size>
		<width>1108</width>
		<height>1478</height>
		<depth>3</depth>
	</size>
	<segmented>0</segmented>
	<object>
		<name>clubs</name>
		<pose>Unspecified</pose>
		<truncated>0</truncated>
		<difficult>0</difficult>
		<bndbox>
			<xmin>330</xmin>
			<ymin>631</ymin>
			<xmax>370</xmax>
			<ymax>674</ymax>
		</bndbox>
	</object>
	<object>
		<name>clubs</name>
		<pose>Unspecified</pose>
		<truncated>0</truncated>
		<difficult>0</difficult>
		<bndbox>
			<xmin>351</xmin>
			<ymin>571</ymin>
			<xmax>430</xmax>
			<ymax>652</ymax>
		</bndbox>
	</object>
	<object>
		<name>clubs</name>
		<pose>Unspecified</pose>
		<truncated>0</truncated>
		<difficult>0</difficult>
		<bndbox>
			<xmin>430</xmin>
			<ymin>514</ymin>
			<xmax>525</xmax>
			<ymax>606</ymax>
		</bndbox>
	</object>
	<object>
		<name>clubs</name>
		<pose>Unspecified</pose>
		<truncated>0</truncated>
		<difficult>0</difficult>
		<bndbox>
			<xmin>463</xmin>
			<ymin>664</ymin>
			<xmax>556</xmax>
			<ymax>742</ymax>
		</bndbox>
	</object>
	<object>
		<name>clubs</name>
		<pose>Unspecified</pose>
		<truncated>0</truncated>
		<difficult>0</difficult>
		<bndbox>
			<xmin>591</xmin>
			<ymin>756</ymin>
			<xmax>668</xmax>
			<ymax>840</ymax>
		</bndbox>
	</object>
	<object>
		<name>clubs</name>
		<pose>Unspecified</pose>
		<truncated>0</truncated>
		<difficult>0</difficult>
		<bndbox>
			<xmin>515</xmin>
			<ymin>807</ymin>
			<xmax>594</xmax>
			<ymax>887</ymax>
		</bndbox>
	</object>
	<object>
		<name>clubs</name>
		<pose>Unspecified</pose>
		<truncated>0</truncated>
		<difficult>0</difficult>
		<bndbox>
			<xmin>655</xmin>
			<ymin>733</ymin>
			<xmax>693</xmax>
			<ymax>769</ymax>
		</bndbox>
	</object>
</annotation>
